retailterms/__init__.py
retailterms/retailterms.py
retailterms/rt.xlsx
retailterms-0.0.22.dist-info/METADATA
retailterms-0.0.22.dist-info/WHEEL
retailterms-0.0.22.dist-info/top_level.txt
retailterms-0.0.22.dist-info/RECORD
