Metadata-Version: 2.1
Name: retailterms
Version: 0.0.22
Summary: NLP Library to find Retail terms
Author: Marcel Tino
Author-email: <marceltino92@gmail.com>
Keywords: retail,retailterms
Requires-Dist: pandas
Requires-Dist: spacy
